centauri/__init__.py
centauri-0.0.1.dist-info/METADATA
centauri-0.0.1.dist-info/WHEEL
centauri-0.0.1.dist-info/top_level.txt
centauri-0.0.1.dist-info/RECORD
